{
  "co2e": 0.0004631,
  "co2e_unit": "kg",
  "co2e_calculation_method": "ar4",
  "co2e_calculation_origin": "source",
  "emission_factor": {
    "activity_id": "networking-provider_aws-region_ap_southeast_1",
    "uuid": "6fe6b54f-9425-4e16-815d-fbb3cff3d433",
    "id": "networking-provider_aws-region_ap_southeast_1",
    "access_type": "public",
    "source": "CCF",
    "year": "2022",
    "region": "SG-SIN",
    "category": "Cloud Computing - Networking",
    "lca_activity": "use_phase",
    "data_quality_flags": [
      "notable_methodological_variance"
    ]
  },
  "constituent_gases": {
    "co2e_total": 0.0004631,
    "co2e_other": null,
    "co2": null,
    "ch4": null,
    "n2o": null
  }
}